mlinterpret/__init__.py
mlinterpret/mlinterpret.py
mlinterpret-1.0.dist-info/METADATA
mlinterpret-1.0.dist-info/WHEEL
mlinterpret-1.0.dist-info/licenses/LICENSE.txt
mlinterpret-1.0.dist-info/RECORD
